README.txt
setup.py
djangohelpers/__init__.py
djangohelpers/console_scripts.py
djangohelpers/export_action.py
djangohelpers/lib.py
djangohelpers/middleware.py
djangohelpers/permissions.py
djangohelpers/wsgi.py
djangohelpers.egg-info/PKG-INFO
djangohelpers.egg-info/SOURCES.txt
djangohelpers.egg-info/dependency_links.txt
djangohelpers.egg-info/entry_points.txt
djangohelpers.egg-info/not-zip-safe
djangohelpers.egg-info/top_level.txt
djangohelpers/templatetags/__init__.py
djangohelpers/templatetags/helpful_tags.py