Metadata-Version: 1.0
Name: djangohelpers
Version: 0.19
Summary: a collection of useful middleware, template tags, etc
Home-page: UNKNOWN
Author: Ethan Jucovy
Author-email: ejucovy@gmail.com
License: BSD
Platform: UNKNOWN
